odoo/addons/helpdesk_mgmt_project_stage/README.rst
odoo/addons/helpdesk_mgmt_project_stage/__init__.py
odoo/addons/helpdesk_mgmt_project_stage/__manifest__.py
odoo/addons/helpdesk_mgmt_project_stage/demo/project_task_type.xml
odoo/addons/helpdesk_mgmt_project_stage/i18n/helpdesk_mgmt_project_stage.pot
odoo/addons/helpdesk_mgmt_project_stage/i18n/it.po
odoo/addons/helpdesk_mgmt_project_stage/i18n/pt_BR.po
odoo/addons/helpdesk_mgmt_project_stage/models/__init__.py
odoo/addons/helpdesk_mgmt_project_stage/models/helpdesk_ticket.py
odoo/addons/helpdesk_mgmt_project_stage/models/helpdesk_ticket_stage.py
odoo/addons/helpdesk_mgmt_project_stage/models/project_task.py
odoo/addons/helpdesk_mgmt_project_stage/models/project_task_type.py
odoo/addons/helpdesk_mgmt_project_stage/readme/CONFIGURE.md
odoo/addons/helpdesk_mgmt_project_stage/readme/CONTRIBUTORS.md
odoo/addons/helpdesk_mgmt_project_stage/readme/DESCRIPTION.md
odoo/addons/helpdesk_mgmt_project_stage/readme/USAGE.md
odoo/addons/helpdesk_mgmt_project_stage/static/description/icon.png
odoo/addons/helpdesk_mgmt_project_stage/static/description/index.html
odoo/addons/helpdesk_mgmt_project_stage/tests/__init__.py
odoo/addons/helpdesk_mgmt_project_stage/tests/test_helpdesk_mgmt_project_stage.py
odoo/addons/helpdesk_mgmt_project_stage/views/helpdesk_ticket_state.xml
odoo/addons/helpdesk_mgmt_project_stage/views/project_task_type.xml
odoo_addon_helpdesk_mgmt_project_stage-16.0.1.0.0.6.dist-info/METADATA
odoo_addon_helpdesk_mgmt_project_stage-16.0.1.0.0.6.dist-info/WHEEL
odoo_addon_helpdesk_mgmt_project_stage-16.0.1.0.0.6.dist-info/top_level.txt
odoo_addon_helpdesk_mgmt_project_stage-16.0.1.0.0.6.dist-info/RECORD
