Metadata-Version: 2.1
Name: odoo-addon-helpdesk_mgmt_project_stage
Version: 16.0.1.0.0.6
Summary: Keeps the stages of tickets and tasks in sync
Home-page: https://github.com/OCA/helpdesk
Author: Hunki Enterprises BV, Odoo Community Association (OCA)
Author-email: support@odoo-community.org
License: AGPL-3
Classifier: Programming Language :: Python
Classifier: Framework :: Odoo
Classifier: Framework :: Odoo :: 16.0
Classifier: License :: OSI Approved :: GNU Affero General Public License v3
Classifier: Development Status :: 3 - Alpha
Requires-Python: >=3.10
Requires-Dist: odoo-addon-helpdesk-mgmt-project<16.1dev,>=16.0dev
Requires-Dist: odoo<16.1dev,>=16.0a
